[
  {
    "title": "Harry Potter i Kamień Filozoficzny. Gryffindor",
    "author": "J.K. Rowling",
    "publisher": "Media Rodzina",
    "rating": 8.1,
    "numberOfRatings": 69192,
    "numberOfPages": 352,
    "yearOfPublish": 2020
  },
  {
    "title": "Hobbit",
    "author": "J.R.R. Tolkien",
    "publisher": "Zysk i S-ka",
    "rating": 7.7,
    "numberOfRatings": 49362,
    "numberOfPages": 304,
    "yearOfPublish": 2018
  },
  {
    "title": "Ostatnie życzenie",
    "author": "Andrzej Sapkowski",
    "publisher": "superNOWA",
    "rating": 8.4,
    "numberOfRatings": 37220,
    "numberOfPages": 332,
    "yearOfPublish": 2014
  },
  {
    "title": "Gra o tron",
    "author": "George R.R. Martin",
    "publisher": "Zysk i S-ka",
    "rating": 8.4,
    "numberOfRatings": 35829,
    "numberOfPages": 999,
    "yearOfPublish": 2016
  },
  {
    "title": "Krew elfów",
    "author": "Andrzej Sapkowski",
    "publisher": "superNOWA",
    "rating": 8.2,
    "numberOfRatings": 34859,
    "numberOfPages": 340,
    "yearOfPublish": 2014
  },
  {
    "title": "Przed świtem",
    "author": "Stephenie Meyer",
    "publisher": "Wydawnictwo Dolnośląskie",
    "rating": 6.3,
    "numberOfRatings": 33270,
    "numberOfPages": 719,
    "yearOfPublish": 2009
  },
  {
    "title": "Miecz przeznaczenia",
    "author": "Andrzej Sapkowski",
    "publisher": "superNOWA",
    "rating": 8.4,
    "numberOfRatings": 32013,
    "numberOfPages": 400,
    "yearOfPublish": 2014
  },
  {
    "title": "Chrzest ognia",
    "author": "Andrzej Sapkowski",
    "publisher": "superNOWA",
    "rating": 8.4,
    "numberOfRatings": 29684,
    "numberOfPages": 382,
    "yearOfPublish": 2014
  },
  {
    "title": "Drużyna Pierścienia",
    "author": "J.R.R. Tolkien",
    "publisher": "Amber",
    "rating": 8.4,
    "numberOfRatings": 28850,
    "numberOfPages": 448,
    "yearOfPublish": 2012
  },
  {
    "title": "Wieża Jaskółki",
    "author": "Andrzej Sapkowski",
    "publisher": "superNOWA",
    "rating": 8.3,
    "numberOfRatings": 26151,
    "numberOfPages": 488,
    "yearOfPublish": 2014
  },
  {
    "title": "Pani Jeziora",
    "author": "Andrzej Sapkowski",
    "publisher": "superNOWA",
    "rating": 8.2,
    "numberOfRatings": 26051,
    "numberOfPages": 596,
    "yearOfPublish": 2014
  },
  {
    "title": "Czas pogardy",
    "author": "Andrzej Sapkowski",
    "publisher": "superNOWA",
    "rating": 8.2,
    "numberOfRatings": 25496,
    "numberOfPages": 368,
    "yearOfPublish": 2014
  },
  {
    "title": "Powrót Króla",
    "author": "J.R.R. Tolkien",
    "publisher": "Zysk i S-ka",
    "rating": 8.6,
    "numberOfRatings": 24219,
    "numberOfPages": 608,
    "yearOfPublish": 2015
  },
  {
    "title": "Starcie królów",
    "author": "George R.R. Martin",
    "publisher": "Zysk i S-ka",
    "rating": 8.4,
    "numberOfRatings": 23951,
    "numberOfPages": 1084,
    "yearOfPublish": 2019
  },
  {
    "title": "Miasto kości",
    "author": "Cassandra Clare",
    "publisher": "Mag",
    "rating": 7.8,
    "numberOfRatings": 23952,
    "numberOfPages": 528,
    "yearOfPublish": 2017
  },
  {
    "title": "Metro 2033",
    "author": "Dmitry Glukhovsky",
    "publisher": "Insignis",
    "rating": 7.8,
    "numberOfRatings": 20839,
    "numberOfPages": 578,
    "yearOfPublish": 2018
  },
  {
    "title": "Nawałnica mieczy: Stal i śnieg",
    "author": "George R.R. Martin",
    "publisher": "Zysk i S-ka",
    "rating": 8.4,
    "numberOfRatings": 19902,
    "numberOfPages": 736,
    "yearOfPublish": 2013
  },
  {
    "title": "Lew, czarownica i stara szafa",
    "author": "Clive Staples Lewis",
    "publisher": "Media Rodzina",
    "rating": 7.3,
    "numberOfRatings": 19893,
    "numberOfPages": 182,
    "yearOfPublish": 2005
  },
  {
    "title": "Nawałnica mieczy: Krew i złoto",
    "author": "George R.R. Martin",
    "publisher": "Zysk i S-ka",
    "rating": 8.5,
    "numberOfRatings": 19630,
    "numberOfPages": 636,
    "yearOfPublish": 2014
  },
  {
    "title": "Szeptem",
    "author": "Becca Fitzpatrick",
    "publisher": "Otwarte",
    "rating": 7.4,
    "numberOfRatings": 18651,
    "numberOfPages": 328,
    "yearOfPublish": 2010
  },
  {
    "title": "Miasto popiołów",
    "author": "Cassandra Clare",
    "publisher": "Mag",
    "rating": 7.9,
    "numberOfRatings": 18191,
    "numberOfPages": 432,
    "yearOfPublish": 2017
  },
  {
    "title": "Niezgodna",
    "author": "Veronica Roth",
    "publisher": "Amber",
    "rating": 7.5,
    "numberOfRatings": 17546,
    "numberOfPages": 352,
    "yearOfPublish": 2014
  },
  {
    "title": "Uczta dla wron: Cienie śmierci",
    "author": "George R.R. Martin",
    "publisher": "Zysk i S-ka",
    "rating": 7.8,
    "numberOfRatings": 17342,
    "numberOfPages": 480,
    "yearOfPublish": 2015
  },
  {
    "title": "Pan Lodowego Ogrodu - tom I",
    "author": "Jarosław Grzędowicz",
    "publisher": "Fabryka Słów",
    "rating": 8.1,
    "numberOfRatings": 16926,
    "numberOfPages": 560,
    "yearOfPublish": 2012
  },
  {
    "title": "Władca Pierścieni",
    "author": "J.R.R. Tolkien",
    "publisher": "Amber",
    "rating": 8.7,
    "numberOfRatings": 16875,
    "numberOfPages": 1024,
    "yearOfPublish": 2015
  },
  {
    "title": "Intruz",
    "author": "Stephenie Meyer",
    "publisher": "Wydawnictwo Dolnośląskie",
    "rating": 7.6,
    "numberOfRatings": 16818,
    "numberOfPages": 568,
    "yearOfPublish": 2013
  },
  {
    "title": "Gildia Magów",
    "author": "Trudi Canavan",
    "publisher": "Galeria Książki",
    "rating": 7.2,
    "numberOfRatings": 16767,
    "numberOfPages": 520,
    "yearOfPublish": 2017
  },
  {
    "title": "Miasto szkła",
    "author": "Cassandra Clare",
    "publisher": "Mag",
    "rating": 8.1,
    "numberOfRatings": 16755,
    "numberOfPages": 544,
    "yearOfPublish": 2017
  },
  {
    "title": "Sezon burz",
    "author": "Andrzej Sapkowski",
    "publisher": "superNOWA",
    "rating": 7.3,
    "numberOfRatings": 16711,
    "numberOfPages": 404,
    "yearOfPublish": 2013
  },
  {
    "title": "Eragon",
    "author": "Christopher Paolini",
    "publisher": "Mag",
    "rating": 6.8,
    "numberOfRatings": 16407,
    "numberOfPages": 496,
    "yearOfPublish": 2019
  },
  {
    "title": "Uczta dla wron: Sieć spisków",
    "author": "George R.R. Martin",
    "publisher": "Zysk i S-ka",
    "rating": 7.9,
    "numberOfRatings": 16238,
    "numberOfPages": 504,
    "yearOfPublish": 2015
  },
  {
    "title": "Taniec ze smokami. Część 1",
    "author": "George R.R. Martin",
    "publisher": "Zysk i S-ka",
    "rating": 8,
    "numberOfRatings": 15310,
    "numberOfPages": 632,
    "yearOfPublish": 2016
  },
  {
    "title": "Taniec ze smokami. Część 2",
    "author": "George R.R. Martin",
    "publisher": "Zysk i S-ka",
    "rating": 8.2,
    "numberOfRatings": 14147,
    "numberOfPages": 688,
    "yearOfPublish": 2016
  },
  {
    "title": "Nowicjuszka",
    "author": "Trudi Canavan",
    "publisher": "Galeria Książki",
    "rating": 7.5,
    "numberOfRatings": 13771,
    "numberOfPages": 520,
    "yearOfPublish": 2012
  },
  {
    "title": "Crescendo",
    "author": "Becca Fitzpatrick",
    "publisher": "Otwarte",
    "rating": 7.6,
    "numberOfRatings": 13034,
    "numberOfPages": 400,
    "yearOfPublish": 2011
  },
  {
    "title": "Pan Lodowego Ogrodu - tom II",
    "author": "Jarosław Grzędowicz",
    "publisher": "Fabryka Słów",
    "rating": 7.9,
    "numberOfRatings": 13015,
    "numberOfPages": 656,
    "yearOfPublish": 2012
  },
  {
    "title": "Wielki Mistrz",
    "author": "Trudi Canavan",
    "publisher": "Galeria Książki",
    "rating": 7.8,
    "numberOfRatings": 12850,
    "numberOfPages": 656,
    "yearOfPublish": 2012
  },
  {
    "title": "Miasto Upadłych Aniołów",
    "author": "Cassandra Clare",
    "publisher": "Mag",
    "rating": 7.9,
    "numberOfRatings": 12684,
    "numberOfPages": 448,
    "yearOfPublish": 2013
  },
  {
    "title": "Zbuntowana",
    "author": "Veronica Roth",
    "publisher": "Amber",
    "rating": 7.3,
    "numberOfRatings": 12527,
    "numberOfPages": 368,
    "yearOfPublish": 2015
  },
  {
    "title": "Narrenturm",
    "author": "Andrzej Sapkowski",
    "publisher": "Niezależna Oficyna Wydawnicza NOWA",
    "rating": 7.6,
    "numberOfRatings": 12484,
    "numberOfPages": 593,
    "yearOfPublish": 2002
  },
  {
    "title": "Kroniki Jakuba Wędrowycza",
    "author": "Andrzej Pilipiuk",
    "publisher": "Fabryka Słów",
    "rating": 7.1,
    "numberOfRatings": 12094,
    "numberOfPages": 296,
    "yearOfPublish": 2011
  },
  {
    "title": "Dziedzictwo",
    "author": "Christopher Paolini",
    "publisher": "Mag",
    "rating": 7.2,
    "numberOfRatings": 12087,
    "numberOfPages": 816,
    "yearOfPublish": 2019
  },
  {
    "title": "Solaris",
    "author": "Stanisław Lem",
    "publisher": "Wydawnictwo Literackie",
    "rating": 7.8,
    "numberOfRatings": 11837,
    "numberOfPages": 340,
    "yearOfPublish": 2012
  },
  {
    "title": "Pan Lodowego Ogrodu - tom III",
    "author": "Jarosław Grzędowicz",
    "publisher": "Fabryka Słów",
    "rating": 8.1,
    "numberOfRatings": 11576,
    "numberOfPages": 512,
    "yearOfPublish": 2012
  },
  {
    "title": "Naznaczona",
    "author": "Kristin Cast, Phyllis Christine Cast",
    "publisher": "Książnica",
    "rating": 6.4,
    "numberOfRatings": 11314,
    "numberOfPages": 328,
    "yearOfPublish": 2009
  },
  {
    "title": "Achaja - Tom I",
    "author": "Andrzej Ziemiański",
    "publisher": "Fabryka Słów",
    "rating": 7.1,
    "numberOfRatings": 11302,
    "numberOfPages": 688,
    "yearOfPublish": 2011
  },
  {
    "title": "Najstarszy",
    "author": "Christopher Paolini",
    "publisher": "Mag",
    "rating": 7,
    "numberOfRatings": 11122,
    "numberOfPages": 688,
    "yearOfPublish": 2019
  },
  {
    "title": "Dwie wieże",
    "author": "J.R.R. Tolkien",
    "publisher": "Zysk i S-ka",
    "rating": 8.6,
    "numberOfRatings": 11056,
    "numberOfPages": 501,
    "yearOfPublish": 2015
  },
  {
    "title": "Cisza",
    "author": "Becca Fitzpatrick",
    "publisher": "Otwarte",
    "rating": 7.8,
    "numberOfRatings": 11056,
    "numberOfPages": 400,
    "yearOfPublish": 2011
  },
  {
    "title": "Kolor magii",
    "author": "Terry Pratchett",
    "publisher": "Prószyński i S-ka",
    "rating": 7.1,
    "numberOfRatings": 11017,
    "numberOfPages": 208,
    "yearOfPublish": 1994
  },
  {
    "title": "Złodziej Pioruna",
    "author": "Rick Riordan",
    "publisher": "Galeria Książki",
    "rating": 8,
    "numberOfRatings": 10966,
    "numberOfPages": 360,
    "yearOfPublish": 2016
  },
  {
    "title": "Książę Kaspian",
    "author": "Clive Staples Lewis",
    "publisher": "Media Rodzina",
    "rating": 7,
    "numberOfRatings": 10943,
    "numberOfPages": 222,
    "yearOfPublish": 2008
  },
  {
    "title": "Silmarillion. Wersja ilustrowana",
    "author": "J.R.R. Tolkien",
    "publisher": "Zysk i S-ka",
    "rating": 8,
    "numberOfRatings": 10467,
    "numberOfPages": 482,
    "yearOfPublish": 2017
  },
  {
    "title": "Miasto zagubionych dusz",
    "author": "Cassandra Clare",
    "publisher": "Mag",
    "rating": 8.2,
    "numberOfRatings": 10465,
    "numberOfPages": 556,
    "yearOfPublish": 2013
  },
  {
    "title": "Diuna",
    "author": "Frank Herbert",
    "publisher": "Rebis",
    "rating": 8.2,
    "numberOfRatings": 10385,
    "numberOfPages": 784,
    "yearOfPublish": 2020
  },
  {
    "title": "Gra Endera",
    "author": "Orson Scott Card",
    "publisher": "Prószyński i S-ka",
    "rating": 8,
    "numberOfRatings": 10282,
    "numberOfPages": 328,
    "yearOfPublish": 2009
  },
  {
    "title": "Metro 2034",
    "author": "Dmitry Glukhovsky",
    "publisher": "Insignis",
    "rating": 6.6,
    "numberOfRatings": 10209,
    "numberOfPages": null,
    "yearOfPublish": 2018
  },
  {
    "title": "Boży bojownicy",
    "author": "Andrzej Sapkowski",
    "publisher": "Niezależna Oficyna Wydawnicza NOWA",
    "rating": 7.7,
    "numberOfRatings": 10026,
    "numberOfPages": 587,
    "yearOfPublish": 2004
  },
  {
    "title": "Pan Lodowego Ogrodu - tom IV",
    "author": "Jarosław Grzędowicz",
    "publisher": "Fabryka Słów",
    "rating": 8.1,
    "numberOfRatings": 9908,
    "numberOfPages": 880,
    "yearOfPublish": 2012
  },
  {
    "title": "Mechaniczny anioł",
    "author": "Cassandra Clare",
    "publisher": "Mag",
    "rating": 8.1,
    "numberOfRatings": 9873,
    "numberOfPages": 472,
    "yearOfPublish": 2013
  },
  {
    "title": "Wierna",
    "author": "Veronica Roth",
    "publisher": "Amber",
    "rating": 7.2,
    "numberOfRatings": 9723,
    "numberOfPages": 380,
    "yearOfPublish": 2014
  },
  {
    "title": "Dotyk Julii",
    "author": "Tahereh Mafi",
    "publisher": "Otwarte",
    "rating": 7.7,
    "numberOfRatings": 9684,
    "numberOfPages": 336,
    "yearOfPublish": 2014
  },
  {
    "title": "Wywiad z wampirem",
    "author": "Anne Rice",
    "publisher": "Rebis",
    "rating": 7.3,
    "numberOfRatings": 9618,
    "numberOfPages": 400,
    "yearOfPublish": 2018
  },
  {
    "title": "Ruiny Gorlanu",
    "author": "John Flanagan",
    "publisher": "Jaguar",
    "rating": 7.8,
    "numberOfRatings": 9567,
    "numberOfPages": 320,
    "yearOfPublish": 2009
  },
  {
    "title": "Szklany tron",
    "author": "Sarah J. Maas",
    "publisher": "Uroboros",
    "rating": 7.9,
    "numberOfRatings": 9557,
    "numberOfPages": null,
    "yearOfPublish": 2019
  },
  {
    "title": "Więzień labiryntu",
    "author": "James Dashner",
    "publisher": "Papierowy Księżyc",
    "rating": 7.7,
    "numberOfRatings": 9499,
    "numberOfPages": 424,
    "yearOfPublish": 2014
  },
  {
    "title": "Brisingr",
    "author": "Christopher Paolini",
    "publisher": "Mag",
    "rating": 7.1,
    "numberOfRatings": 9451,
    "numberOfPages": 704,
    "yearOfPublish": 2019
  },
  {
    "title": "Achaja - Tom II",
    "author": "Andrzej Ziemiański",
    "publisher": "Fabryka Słów",
    "rating": 7.1,
    "numberOfRatings": 9200,
    "numberOfPages": 644,
    "yearOfPublish": 2011
  },
  {
    "title": "Malowany człowiek: Księga I",
    "author": "Peter V. Brett",
    "publisher": "Fabryka Słów",
    "rating": 7.9,
    "numberOfRatings": 8932,
    "numberOfPages": 504,
    "yearOfPublish": 2008
  },
  {
    "title": "Lux perpetua",
    "author": "Andrzej Sapkowski",
    "publisher": "Niezależna Oficyna Wydawnicza NOWA",
    "rating": 7.7,
    "numberOfRatings": 8679,
    "numberOfPages": 560,
    "yearOfPublish": 2006
  },
  {
    "title": "Marsjanin",
    "author": "Andy Weir",
    "publisher": "Akurat",
    "rating": 7.9,
    "numberOfRatings": 8627,
    "numberOfPages": 384,
    "yearOfPublish": 2014
  },
  {
    "title": "Drugie życie Bree Tanner",
    "author": "Stephenie Meyer",
    "publisher": "Wydawnictwo Dolnośląskie",
    "rating": 5.8,
    "numberOfRatings": 8610,
    "numberOfPages": 201,
    "yearOfPublish": 2010
  },
  {
    "title": "Finale",
    "author": "Becca Fitzpatrick",
    "publisher": "Otwarte",
    "rating": 8,
    "numberOfRatings": 8604,
    "numberOfPages": 424,
    "yearOfPublish": 2012
  },
  {
    "title": "Amerykańscy bogowie",
    "author": "Neil Gaiman",
    "publisher": "Mag",
    "rating": 7.4,
    "numberOfRatings": 8545,
    "numberOfPages": 608,
    "yearOfPublish": 2016
  },
  {
    "title": "Bastion",
    "author": "Stephen King",
    "publisher": "Albatros",
    "rating": 7.9,
    "numberOfRatings": 8514,
    "numberOfPages": 1166,
    "yearOfPublish": 2018
  },
  {
    "title": "Szeptucha",
    "author": "Katarzyna Berenika Miszczuk",
    "publisher": "W.A.B.",
    "rating": 7.2,
    "numberOfRatings": 8473,
    "numberOfPages": 416,
    "yearOfPublish": 2016
  },
  {
    "title": "Dallas '63",
    "author": "Stephen King",
    "publisher": "Prószyński i S-ka",
    "rating": 8.2,
    "numberOfRatings": 8406,
    "numberOfPages": 864,
    "yearOfPublish": 2011
  },
  {
    "title": "Achaja - Tom III",
    "author": "Andrzej Ziemiański",
    "publisher": "Fabryka Słów",
    "rating": 6.7,
    "numberOfRatings": 8363,
    "numberOfPages": 409,
    "yearOfPublish": 2012
  },
  {
    "title": "Vampire Academy",
    "author": "Richelle Mead",
    "publisher": "Penguin Books",
    "rating": 7.7,
    "numberOfRatings": 8294,
    "numberOfPages": 332,
    "yearOfPublish": 2007
  },
  {
    "title": "Kłamca",
    "author": "Jakub Ćwiek",
    "publisher": "Sine Qua Non",
    "rating": 7.2,
    "numberOfRatings": 8283,
    "numberOfPages": null,
    "yearOfPublish": 2018
  },
  {
    "title": "Zdradzona",
    "author": "Kristin Cast, Phyllis Christine Cast",
    "publisher": "Książnica",
    "rating": 6.6,
    "numberOfRatings": 8266,
    "numberOfPages": 348,
    "yearOfPublish": 2010
  },
  {
    "title": "Blask fantastyczny",
    "author": "Terry Pratchett",
    "publisher": "Prószyński i S-ka",
    "rating": 7.4,
    "numberOfRatings": 8237,
    "numberOfPages": 236,
    "yearOfPublish": 1995
  },
  {
    "title": "Czerwona Królowa",
    "author": "Victoria Aveyard",
    "publisher": "Moondrive",
    "rating": 7.5,
    "numberOfRatings": 8187,
    "numberOfPages": 488,
    "yearOfPublish": 2015
  },
  {
    "title": "Coś się kończy, coś się zaczyna",
    "author": "Andrzej Sapkowski",
    "publisher": "superNOWA",
    "rating": 7.4,
    "numberOfRatings": 8013,
    "numberOfPages": 299,
    "yearOfPublish": 2000
  },
  {
    "title": "Droga",
    "author": "Cormac McCarthy",
    "publisher": "Wydawnictwo Literackie",
    "rating": 7.7,
    "numberOfRatings": 7990,
    "numberOfPages": 272,
    "yearOfPublish": 2019
  },
  {
    "title": "Mort",
    "author": "Terry Pratchett",
    "publisher": "Prószyński i S-ka",
    "rating": 7.6,
    "numberOfRatings": 7987,
    "numberOfPages": 262,
    "yearOfPublish": 1996
  },
  {
    "title": "Klątwa Tytana",
    "author": "Rick Riordan",
    "publisher": "Galeria Książki",
    "rating": 8.2,
    "numberOfRatings": 7950,
    "numberOfPages": 312,
    "yearOfPublish": 2016
  },
  {
    "title": "Ja, inkwizytor. Sługa Boży",
    "author": "Jacek Piekara",
    "publisher": "Fabryka Słów",
    "rating": 7.2,
    "numberOfRatings": 7931,
    "numberOfPages": 385,
    "yearOfPublish": 2015
  },
  {
    "title": "Roland",
    "author": "Stephen King",
    "publisher": "Albatros",
    "rating": 6.9,
    "numberOfRatings": 7908,
    "numberOfPages": 320,
    "yearOfPublish": 2017
  },
  {
    "title": "Mechaniczny książę",
    "author": "Cassandra Clare",
    "publisher": "Mag",
    "rating": 8.4,
    "numberOfRatings": 7871,
    "numberOfPages": 464,
    "yearOfPublish": 2013
  },
  {
    "title": "Malowany człowiek: Księga II",
    "author": "Peter V. Brett",
    "publisher": "Fabryka Słów",
    "rating": 8,
    "numberOfRatings": 7808,
    "numberOfPages": 320,
    "yearOfPublish": 2009
  },
  {
    "title": "Siewca Wiatru",
    "author": "Maja Lidia Kossakowska",
    "publisher": "Fabryka Słów",
    "rating": 7.4,
    "numberOfRatings": 7796,
    "numberOfPages": 656,
    "yearOfPublish": 2014
  },
  {
    "title": "Czarownik Iwanow",
    "author": "Andrzej Pilipiuk",
    "publisher": "Fabryka Słów",
    "rating": 7.1,
    "numberOfRatings": 7793,
    "numberOfPages": 272,
    "yearOfPublish": 2011
  },
  {
    "title": "Delirium",
    "author": "Lauren Oliver",
    "publisher": "Moondrive",
    "rating": 7.8,
    "numberOfRatings": 7786,
    "numberOfPages": 360,
    "yearOfPublish": 2012
  },
  {
    "title": "Morze Potworów",
    "author": "Rick Riordan",
    "publisher": "Galeria Książki",
    "rating": 7.9,
    "numberOfRatings": 7711,
    "numberOfPages": 280,
    "yearOfPublish": 2016
  },
  {
    "title": "Upadli",
    "author": "Lauren Kate",
    "publisher": "Mag",
    "rating": 6.8,
    "numberOfRatings": 7663,
    "numberOfPages": 480,
    "yearOfPublish": 2010
  },
  {
    "title": "Miasto niebiańskiego ognia",
    "author": "Cassandra Clare",
    "publisher": "Mag",
    "rating": 8.4,
    "numberOfRatings": 7656,
    "numberOfPages": 702,
    "yearOfPublish": 2014
  },
  {
    "title": "Droga Królów",
    "author": "Brandon Sanderson",
    "publisher": "Mag",
    "rating": 8.9,
    "numberOfRatings": 7556,
    "numberOfPages": 1136,
    "yearOfPublish": 2019
  },
  {
    "title": "Bitwa w Labiryncie",
    "author": "Rick Riordan",
    "publisher": "Galeria Książki",
    "rating": 8.3,
    "numberOfRatings": 7360,
    "numberOfPages": 364,
    "yearOfPublish": 2016
  },
  {
    "title": "Pod kopułą",
    "author": "Stephen King",
    "publisher": "Prószyński i S-ka",
    "rating": 7.4,
    "numberOfRatings": 7341,
    "numberOfPages": 928,
    "yearOfPublish": 2010
  },
  {
    "title": "Wybrana",
    "author": "Kristin Cast, Phyllis Christine Cast",
    "publisher": "Książnica",
    "rating": 6.7,
    "numberOfRatings": 7202,
    "numberOfPages": 296,
    "yearOfPublish": 2010
  },
  {
    "title": "Weźmisz czarno kure...",
    "author": "Andrzej Pilipiuk",
    "publisher": "Fabryka Słów",
    "rating": 7.3,
    "numberOfRatings": 7196,
    "numberOfPages": 392,
    "yearOfPublish": 2011
  },
  {
    "title": "Nigdziebądź",
    "author": "Neil Gaiman",
    "publisher": "Mag",
    "rating": 7.4,
    "numberOfRatings": 7123,
    "numberOfPages": 384,
    "yearOfPublish": 2016
  },
  {
    "title": "Czarnoksiężnik z Archipelagu",
    "author": "Ursula K. Le Guin",
    "publisher": "Prószyński i S-ka",
    "rating": 7.1,
    "numberOfRatings": 7115,
    "numberOfPages": 240,
    "yearOfPublish": 2010
  },
  {
    "title": "Ostatni Olimpijczyk",
    "author": "Rick Riordan",
    "publisher": "Galeria Książki",
    "rating": 8.5,
    "numberOfRatings": 7089,
    "numberOfPages": 376,
    "yearOfPublish": 2016
  },
  {
    "title": "Osobliwy dom pani Peregrine",
    "author": "Ransom Riggs",
    "publisher": "Media Rodzina",
    "rating": 7.2,
    "numberOfRatings": 7077,
    "numberOfPages": 400,
    "yearOfPublish": 2016
  },
  {
    "title": "Ja, inkwizytor. Młot na czarownice",
    "author": "Jacek Piekara",
    "publisher": "Fabryka Słów",
    "rating": 7.3,
    "numberOfRatings": 6917,
    "numberOfPages": 352,
    "yearOfPublish": 2015
  },
  {
    "title": "Mechaniczna księżniczka",
    "author": "Cassandra Clare",
    "publisher": "Mag",
    "rating": 8.6,
    "numberOfRatings": 6862,
    "numberOfPages": 400,
    "yearOfPublish": 2013
  },
  {
    "title": "Pamiętniki Wampirów Księga 1: Przebudzenie walka szał",
    "author": "Lisa Jane Smith",
    "publisher": "Amber",
    "rating": 6.2,
    "numberOfRatings": 6739,
    "numberOfPages": 508,
    "yearOfPublish": 2011
  },
  {
    "title": "Gwiezdny pył",
    "author": "Neil Gaiman",
    "publisher": "Mag",
    "rating": 7,
    "numberOfRatings": 6715,
    "numberOfPages": 200,
    "yearOfPublish": 2016
  },
  {
    "title": "Korona w mroku",
    "author": "Sarah J. Maas",
    "publisher": "Uroboros",
    "rating": 8.2,
    "numberOfRatings": 6708,
    "numberOfPages": 495,
    "yearOfPublish": 2014
  },
  {
    "title": "Siostrzeniec czarodzieja",
    "author": "Clive Staples Lewis",
    "publisher": "Media Rodzina",
    "rating": 7.3,
    "numberOfRatings": 6705,
    "numberOfPages": 200,
    "yearOfPublish": 2008
  },
  {
    "title": "Koń i jego chłopiec",
    "author": "Clive Staples Lewis",
    "publisher": "Media Rodzina",
    "rating": 7.2,
    "numberOfRatings": 6583,
    "numberOfPages": 215,
    "yearOfPublish": 2008
  },
  {
    "title": "Uczennica maga",
    "author": "Trudi Canavan",
    "publisher": "Galeria Książki",
    "rating": 7.3,
    "numberOfRatings": 6573,
    "numberOfPages": 816,
    "yearOfPublish": 2009
  },
  {
    "title": "Koralina",
    "author": "Neil Gaiman",
    "publisher": "Mag",
    "rating": 7.1,
    "numberOfRatings": 6528,
    "numberOfPages": 112,
    "yearOfPublish": 2017
  },
  {
    "title": "Nieposkromiona",
    "author": "Kristin Cast, Phyllis Christine Cast",
    "publisher": "Książnica",
    "rating": 6.8,
    "numberOfRatings": 6358,
    "numberOfPages": 360,
    "yearOfPublish": 2010
  },
  {
    "title": "Pustynna Włócznia: Księga I",
    "author": "Peter V. Brett",
    "publisher": "Fabryka Słów",
    "rating": 7.9,
    "numberOfRatings": 6333,
    "numberOfPages": 528,
    "yearOfPublish": 2010
  },
  {
    "title": "Próby ognia",
    "author": "James Dashner",
    "publisher": "Papierowy Księżyc",
    "rating": 7.7,
    "numberOfRatings": 6329,
    "numberOfPages": 424,
    "yearOfPublish": 2015
  },
  {
    "title": "Ever",
    "author": "Alyson Noël",
    "publisher": "Wydawnictwo Dolnośląskie",
    "rating": 6.5,
    "numberOfRatings": 6328,
    "numberOfPages": 297,
    "yearOfPublish": 2010
  },
  {
    "title": "Równoumagicznienie",
    "author": "Terry Pratchett",
    "publisher": "Prószyński i S-ka",
    "rating": 7.1,
    "numberOfRatings": 6266,
    "numberOfPages": 200,
    "yearOfPublish": 2006
  }
]